mmap_seq_ds/__init__.py
mmap_seq_ds/test_ds.py
mmap_seq_ds-0.1.0.dist-info/WHEEL
mmap_seq_ds-0.1.0.dist-info/METADATA
mmap_seq_ds-0.1.0.dist-info/RECORD
