Metadata-Version: 2.3
Name: mmap-seq-ds
Version: 0.1.0
Summary: Memory-mapped dataset for sequential data.
Author: Jeff Shen
Author-email: Jeff Shen <jshen2014@hotmail.com>
Requires-Dist: msgpack>=1.1.2
Requires-Dist: numpy>=2.4.1
Requires-Dist: torch>=2.10.0
Requires-Python: >=3.12
